adafruit_circuitpython_httpserver-4.7.1.dist-info/licenses/LICENSE
adafruit_httpserver/__init__.py
adafruit_httpserver/authentication.py
adafruit_httpserver/exceptions.py
adafruit_httpserver/headers.py
adafruit_httpserver/interfaces.py
adafruit_httpserver/methods.py
adafruit_httpserver/mime_types.py
adafruit_httpserver/request.py
adafruit_httpserver/response.py
adafruit_httpserver/route.py
adafruit_httpserver/server.py
adafruit_httpserver/status.py
adafruit_circuitpython_httpserver-4.7.1.dist-info/METADATA
adafruit_circuitpython_httpserver-4.7.1.dist-info/WHEEL
adafruit_circuitpython_httpserver-4.7.1.dist-info/top_level.txt
adafruit_circuitpython_httpserver-4.7.1.dist-info/RECORD
